setup.py
ytsearch/__main__.py
ytsearch/lock.py
ytsearch/program.py
ytsearch/settings.py
ytsearch/threads.py
ytsearch/youtube.py
ytsearch.egg-info/PKG-INFO
ytsearch.egg-info/SOURCES.txt
ytsearch.egg-info/dependency_links.txt
ytsearch.egg-info/entry_points.txt
ytsearch.egg-info/not-zip-safe
ytsearch.egg-info/requires.txt
ytsearch.egg-info/top_level.txt
ytsearch/ui/__init__.py
ytsearch/ui/cache_items.py
ytsearch/ui/page.py
ytsearch/ui/playlist.py
ytsearch/ui/playlist_items.py
ytsearch/ui/queue_items.py
ytsearch/ui/search_results.py
ytsearch/ui/settings.py