Metadata-Version: 1.0
Name: ytsearch
Version: 0.3.6
Summary: A program to search and diplay youtube videos.
Home-page: UNKNOWN
Author: Steven J. Core
Author-email: UNKNOWN
License: GPL3.0
Platform: UNKNOWN
